setup.py
recursers/__init__.py
recursers/model.py
recursers/run.py
recursers.egg-info/PKG-INFO
recursers.egg-info/SOURCES.txt
recursers.egg-info/dependency_links.txt
recursers.egg-info/requires.txt
recursers.egg-info/top_level.txt