Metadata-Version: 2.1
Name: recursers
Version: 0.1.2
Summary: Reduce VRAM usage on transformer models
Home-page: 
Author: Max Ng
Author-email: maxnghello@gmail.com
Classifier: Development Status :: 1 - Planning
Classifier: Intended Audience :: Science/Research
Classifier: Operating System :: POSIX :: Linux
Classifier: Programming Language :: Python :: 2
Classifier: Programming Language :: Python :: 2.7
Classifier: Programming Language :: Python :: 3
Classifier: Programming Language :: Python :: 3.4
Classifier: Programming Language :: Python :: 3.5
Classifier: Programming Language :: Python :: 3.10
